eBase32/__init__.py
ebase32-0.0.1.dist-info/licenses/LICENSE
ebase32-0.0.1.dist-info/METADATA
ebase32-0.0.1.dist-info/WHEEL
ebase32-0.0.1.dist-info/top_level.txt
ebase32-0.0.1.dist-info/RECORD
