Metadata-Version: 2.4
Name: eBase32
Version: 0.0.1
Summary: A human-friendly Base32 encoding without ambiguous characters
Author-email: Endkind <endkind.ender@endkind.net>
License: MIT License
Project-URL: Source, https://github.com/Endkind/eBase32
Project-URL: Specification, https://github.com/Endkind/eBase32/blob/main/docs/standard.md
Keywords: base32,encoding,id,url,friendly,no-confusion
Classifier: Programming Language :: Python :: 3
Classifier: Programming Language :: Python :: 3.6
Classifier: License :: OSI Approved :: MIT License
Classifier: Operating System :: OS Independent
Classifier: Intended Audience :: Developers
Classifier: Topic :: Software Development :: Libraries
Requires-Python: >=3.6
License-File: LICENSE
Dynamic: license-file
